{
  "title": "塔罗牌占卜",
  "draw": "抽一张牌",
  "draw3": "抽三张牌",
  "past": "过去",
  "present": "现在",
  "future": "未来",
  "shuffle": "洗牌",
  "seoDescription": "免费在线塔罗牌占卜。仅供娱乐。",
  "howToUse": "使用方法",
  "howToUseTitle": "如何使用塔罗牌",
  "step1Title": "第一步：专注",
  "step1Desc": "想一个问题。",
  "step2Title": "第二步：抽牌",
  "step2Desc": "选择单张或三张牌阵。",
  "step3Title": "第三步：解读",
  "step3Desc": "每张牌都有独特的含义。",
  "keyFeatures": "主要功能",
  "feature1": "单张/三张牌阵",
  "feature2": "过去/现在/未来",
  "feature3": "详细牌义",
  "feature4": "精美设计",
  "feature5": "移动端",
  "feature6": "免费",
  "commonUses": "常见用途",
  "use1": "每日指引",
  "use2": "决策参考",
  "use3": "自我发现",
  "use4": "娱乐",
  "faq": "常见问题",
  "faq1Q": "是真的占卜吗？",
  "faq1A": "仅供娱乐和自我反思。",
  "faq2Q": "可以问任何问题吗？",
  "faq2A": "可以，开放式问题。",
  "faq3Q": "包含哪些牌？",
  "faq3A": "22张大阿尔卡纳牌。"
}