{
  "title": "타로 카드",
  "draw": "한 장 뽑기",
  "draw3": "세 장 뽑기",
  "past": "과거",
  "present": "현재",
  "future": "미래",
  "shuffle": "셔플",
  "seoDescription": "무료 온라인 타로 카드. 한 장 또는 세 장 스프레드로 통찰과 조언을 얻으세요. 메이저 아르카나 카드와 상세한 의미를 제공합니다. 오락 목적입니다.",
  "howToUse": "사용 방법",
  "howToUseTitle": "타로 카드 이용 방법",
  "step1Title": "1단계: 마음 집중하기",
  "step1Desc": "조언을 얻고 싶은 질문이나 삶의 영역에 대해 생각하세요. 마음을 비우고 집중하세요.",
  "step2Title": "2단계: 카드 뽑기",
  "step2Desc": "한 장으로 빠른 통찰을 얻거나, 세 장 스프레드로 과거/현재/미래를 읽어보세요.",
  "step3Title": "3단계: 카드 해석 읽기",
  "step3Desc": "각 카드는 고유한 메시지를 담고 있습니다. 카드는 무작위로 뽑혀 진정한 타로 경험을 제공합니다.",
  "keyFeatures": "주요 기능",
  "feature1": "한 장 및 세 장 스프레드",
  "feature2": "과거/현재/미래 읽기",
  "feature3": "상세한 카드 의미",
  "feature4": "아름다운 카드 디자인",
  "feature5": "모바일 최적화",
  "feature6": "100% 무료",
  "commonUses": "활용 사례",
  "use1": "하루 조언과 자기 성찰",
  "use2": "의사 결정에 대한 통찰",
  "use3": "자기 발견과 성장",
  "use4": "친구들과 즐거운 시간",
  "faq": "자주 묻는 질문",
  "faq1Q": "진짜 타로인가요?",
  "faq1A": "이것은 오락과 자기 성찰을 위한 무작위 디지털 타로 체험입니다.",
  "faq2Q": "어떤 질문이든 해도 되나요?",
  "faq2A": "네, 인생, 관계, 진로, 자기 계발에 관한 열린 질문에 집중하세요.",
  "faq3Q": "어떤 카드가 포함되나요?",
  "faq3A": "바보, 마법사, 연인, 죽음, 세계 등 22장의 메이저 아르카나 카드입니다."
}