{
  "title": "Probador Regex",
  "test": "Probar",
  "copy": "Copiar",
  "clear": "Limpiar",
  "pattern": "Patrón",
  "flags": "Banderas",
  "text": "Texto",
  "matches": "Coincidencias",
  "groups": "Grupos",
  "noMatch": "Sin coincidencias",
  "seoDescription": "Probador regex gratuito. Pruebe expresiones regulares al instante.",
  "howToUse": "Cómo Usar",
  "howToUseTitle": "Cómo Usar el Probador",
  "step1Title": "Paso 1: Patrón",
  "step1Desc": "Ingrese su regex.",
  "step2Title": "Paso 2: Texto",
  "step2Desc": "Ingrese el texto de prueba.",
  "step3Title": "Paso 3: Pruebe",
  "step3Desc": "Vea coincidencias y grupos.",
  "keyFeatures": "Características",
  "feature1": "Prueba instantánea",
  "feature2": "Resaltado de grupos",
  "feature3": "Banderas g,i,m",
  "feature4": "Posiciones",
  "feature5": "Móvil",
  "feature6": "Gratis",
  "commonUses": "Usos",
  "use1": "Validar formatos",
  "use2": "Extraer datos",
  "use3": "Aprender regex",
  "use4": "Buscar/reemplazar",
  "faq": "FAQ",
  "faq1Q": "¿Qué motor usa?",
  "faq1A": "JavaScript regex.",
  "faq2Q": "¿Reemplazo?",
  "faq2A": "Próximamente.",
  "faq3Q": "¿Resaltado?",
  "faq3A": "Sí, con posiciones."
}