{
  "title": "数据大小转换器",
  "convert": "转换",
  "copy": "复制",
  "input": "输入数值",
  "from": "从",
  "to": "到",
  "bytes": "字节",
  "kb": "千字节",
  "mb": "兆字节",
  "gb": "吉字节",
  "tb": "太字节",
  "seoDescription": "免费在线数据大小转换器。",
  "howToUse": "使用方法",
  "howToUseTitle": "如何使用数据转换器",
  "step1Title": "第一步：输入",
  "step1Desc": "输入数值。",
  "step2Title": "第二步：选择",
  "step2Desc": "选择单位。",
  "step3Title": "第三步：结果",
  "step3Desc": "即时转换。",
  "keyFeatures": "主要功能",
  "feature1": "字节到拍字节",
  "feature2": "实时转换",
  "feature3": "二进制/SI模式",
  "feature4": "一键复制",
  "feature5": "移动端",
  "feature6": "免费",
  "commonUses": "常见用途",
  "use1": "文件大小",
  "use2": "存储规划",
  "use3": "带宽计算",
  "use4": "计算机教育",
  "faq": "常见问题",
  "faq1Q": "二进制还是SI？",
  "faq1A": "二进制(1KB=1024B)。",
  "faq2Q": "GB有多少MB？",
  "faq2A": "二进制: 1GB=1024MB。",
  "faq3Q": "可以转换小数吗？",
  "faq3A": "可以，例如1.5GB。"
}